usaddress/__init__.py
usaddress/usaddr.crfsuite
agrc_usaddress-0.6.1.dist-info/LICENSE
agrc_usaddress-0.6.1.dist-info/METADATA
agrc_usaddress-0.6.1.dist-info/WHEEL
agrc_usaddress-0.6.1.dist-info/top_level.txt
agrc_usaddress-0.6.1.dist-info/RECORD
